cybersightsh/__init__.py
cybersightsh/__main__.py
cybersightsh/terminal.py
cybersightsh-1.0.0.dist-info/licenses/LICENSE
cybersightsh-1.0.0.dist-info/METADATA
cybersightsh-1.0.0.dist-info/WHEEL
cybersightsh-1.0.0.dist-info/entry_points.txt
cybersightsh-1.0.0.dist-info/top_level.txt
cybersightsh-1.0.0.dist-info/RECORD
