Metadata-Version: 2.4
Name: cybersightsh
Version: 1.0.0
Summary: A userguide custom terminal with colors, autocompletion, and basic shell commands.
Author: Cybersight
License: MIT
Keywords: terminal shell custom cybersight cli
Classifier: Programming Language :: Python :: 3
Classifier: License :: OSI Approved :: MIT License
Classifier: Operating System :: OS Independent
Requires-Python: >=3.8
License-File: LICENSE
Requires-Dist: prompt_toolkit
Requires-Dist: colorama
Dynamic: author
Dynamic: classifier
Dynamic: description
Dynamic: description-content-type
Dynamic: keywords
Dynamic: license
Dynamic: license-file
Dynamic: requires-dist
Dynamic: requires-python
Dynamic: summary
